math_mcp_server/__init__.py
math_mcp_server/main.py
math_mcp_server-0.1.0.dist-info/METADATA
math_mcp_server-0.1.0.dist-info/WHEEL
math_mcp_server-0.1.0.dist-info/entry_points.txt
math_mcp_server-0.1.0.dist-info/RECORD
