Metadata-Version: 2.4
Name: math-mcp-server
Version: 0.1.0
Summary: Math operations MCP server
Author-email: Malaviya Harshil <malaviyah.218@example.com>
Requires-Python: >=3.10
Requires-Dist: fastmcp>=0.1.0
Requires-Dist: mcp>=0.1.0
